Metadata-Version: 2.1
Name: spatialmath-python
Version: 1.1.15
Summary: Provides spatial maths capability for Python.
Author-email: Peter Corke <rvc@petercorke.com>
Project-URL: Homepage, https://github.com/bdaiinstitute/spatialmath-python
Project-URL: Bug Tracker, https://github.com/bdaiinstitute/spatialmath-python/issues
Project-URL: Documentation, https://bdaiinstitute.github.io/spatialmath-python/
Project-URL: Source, https://github.com/bdaiinstitute/spatialmath-python
Keywords: spatial-math,spatial math,SO2,SE2,SO3,SE3,SO(2),SE(2),SO(3),SE(3),twist,product of exponential,translation,orientation,angle-axis,Lie group,skew symmetric matrix,pose,translation,rotation matrix,rigid body transform,homogeneous transformation,Euler angles,roll-pitch-yaw angles,quaternion,unit-quaternion,robotics,robot vision,computer vision
Classifier: Development Status :: 5 - Production/Stable
Classifier: Intended Audience :: Developers
Classifier: Programming Language :: Python :: 3.7
Classifier: Programming Language :: Python :: 3.8
Classifier: Programming Language :: Python :: 3.9
Classifier: Programming Language :: Python :: 3.10
Classifier: Programming Language :: Python :: 3.11
Classifier: Programming Language :: Python :: 3.12
Classifier: License :: OSI Approved :: MIT License
Classifier: Operating System :: OS Independent
Requires-Python: >=3.7
License-File: LICENSE
Requires-Dist: numpy>=1.22
Requires-Dist: scipy
Requires-Dist: matplotlib
Requires-Dist: ansitable
Requires-Dist: typing_extensions
Requires-Dist: pre-commit
Provides-Extra: dev
Requires-Dist: sympy; extra == "dev"
Requires-Dist: pytest; extra == "dev"
Requires-Dist: pytest-timeout; extra == "dev"
Requires-Dist: pytest-xvfb; extra == "dev"
Requires-Dist: coverage; extra == "dev"
Requires-Dist: flake8; extra == "dev"
Provides-Extra: docs
Requires-Dist: sphinx; extra == "docs"
Requires-Dist: sphinx-rtd-theme; extra == "docs"
Requires-Dist: sphinx-autorun; extra == "docs"
Requires-Dist: sphinxcontrib-jsmath; extra == "docs"
Requires-Dist: sphinx-favicon; extra == "docs"
Requires-Dist: sphinx-autodoc-typehints; extra == "docs"
Provides-Extra: ros-humble
Requires-Dist: matplotlib==3.5.1; extra == "ros-humble"
Requires-Dist: numpy<2; extra == "ros-humble"
